exoplasim/Alderaan_surf_0129.sra
exoplasim/Alderaan_surf_0172.sra
exoplasim/COPYING
exoplasim/Example_surf_0129.sra
exoplasim/Example_surf_0172.sra
exoplasim/F90_INTEGER
exoplasim/F90_REAL
exoplasim/FAQ
exoplasim/Mountains_surf_0129.sra
exoplasim/Mountains_surf_0172.sra
exoplasim/NEW_IN_VERSION_17
exoplasim/PlanetGrid-Mountains.ipynb
exoplasim/PlanetGrid.ipynb
exoplasim/README
exoplasim/README_COUPLING_PLASIM_PUMA
exoplasim/README_MAC_USER
exoplasim/README_UBUNTU
exoplasim/README_WINDOWS_USER
exoplasim/T21.nc
exoplasim/__init__.py
exoplasim/cc_check.c
exoplasim/cc_check.x
exoplasim/cleancat
exoplasim/cleanplasim
exoplasim/cleanpuma
exoplasim/cleansam
exoplasim/cmdpuma
exoplasim/cmf.csv
exoplasim/colormatch.py
exoplasim/compile.sh
exoplasim/configure.sh
exoplasim/constants.py
exoplasim/csub.c
exoplasim/exoplasim_tutorial.ipynb
exoplasim/f90check.f90
exoplasim/f90check.x
exoplasim/filesupport.py
exoplasim/gcmt.py
exoplasim/index.html
exoplasim/make_most
exoplasim/makecheck
exoplasim/makedebug
exoplasim/makestellarspec.py
exoplasim/most.c
exoplasim/most_compiler
exoplasim/most_compiler_mpi
exoplasim/most_debug_options
exoplasim/most_info.txt
exoplasim/most_precision_options
exoplasim/most_precision_optionsx
exoplasim/pRT.py
exoplasim/pyburn.py
exoplasim/pyfft.f90
exoplasim/pyfft991.f90
exoplasim/quickprocess.py
exoplasim/randomcontinents.py
exoplasim/samplemtplanet.jpg
exoplasim/samplemtplanet.png
exoplasim/sampleplanet.jpg
exoplasim/surfacespecs.py
exoplasim/wvref.txt
exoplasim/basespecs/USGSaspenforest.npy
exoplasim/basespecs/USGSaspenleaf.npy
exoplasim/basespecs/USGSaspentop.npy
exoplasim/basespecs/USGSocean.npy
exoplasim/basespecs/USGSspurge.npy
exoplasim/basespecs/andesitefine.npy
exoplasim/basespecs/andesitesolid.npy
exoplasim/basespecs/basaltsolid.npy
exoplasim/basespecs/brownsand.npy
exoplasim/basespecs/clearice.npy
exoplasim/basespecs/coarsesnow.npy
exoplasim/basespecs/dunesand.npy
exoplasim/basespecs/finesnow.npy
exoplasim/basespecs/frost.npy
exoplasim-3.4.2.dist-info/METADATA
exoplasim-3.4.2.dist-info/WHEEL
exoplasim-3.4.2.dist-info/licenses/LICENSE.TXT
exoplasim-3.4.2.dist-info/RECORD
