Metadata-Version: 2.4
Name: exoplasim
Version: 3.4.2
Summary: Exoplanet GCM
Project-URL: Documentation, https://exoplasim.readthedocs.io
Project-URL: Repository, https://github.com/alphaparrot/ExoPlaSim.git
Project-URL: Issues, https://github.com/alphaparrot/ExoPlaSim/issues
Author: Maureen J. Cohen, Edilbert Kirk, Harmut Borth, Frank Lunkeit
Author-email: Adiv Paradise <paradise.astro@gmail.com>
Maintainer-email: Adiv Paradise <paradise.astro@gmail.com>
License-File: LICENSE.TXT
Keywords: GCM,astronomy,climate,exoplanet,science,simulation,space,weather
Classifier: License :: OSI Approved :: GNU General Public License v2 (GPLv2)
Classifier: Programming Language :: Python :: 3.8
Classifier: Programming Language :: Python :: 3.9
Classifier: Programming Language :: Python :: 3.10
Classifier: Programming Language :: Python :: 3.11
Classifier: Programming Language :: Python :: 3.12
Requires-Python: >=3.8
Requires-Dist: meson
Requires-Dist: ninja
Requires-Dist: numpy>=1.22
Requires-Dist: scipy>=1.6.0
